haven/__init__.py
haven/run.py
haven/pb/__init__.py
haven/pb/manager_pb2.py
haven/pb/manager_pb2_grpc.py
havenllm-0.1.dist-info/METADATA
havenllm-0.1.dist-info/WHEEL
havenllm-0.1.dist-info/top_level.txt
havenllm-0.1.dist-info/RECORD
