Metadata-Version: 2.1
Name: havenllm
Version: 0.1
Summary: Haven SDK
Author: Konstantin Hohr
Author-email: hello@havenllm.com
